{
  "uuid": "7732aaf0-82f8-4757-b86e-28784359191e",
  "shortName": "Silly Watches",
  "longName": "Ministry Of Silly Watches",
  "companyName": "Olivier Mehani",
  "versionCode": 1,
  "versionLabel": "1.0",
  "watchapp": {
    "watchface": true
  },
  "appKeys": {
    "dummy": 0
  },
  "resources": {
    "media": [
      {
	"menuIcon": true,
	"name": "ICON",
	"file": "images/sillywalks/icon.png",
	"type": "png"
      },
      {
	"name": "FACE_0",
	"file": "images/sillywalks/00.png",
	"type": "png"
      },
      {
	"name": "FACE_1",
	"file": "images/sillywalks/01.png",
	"type": "png"
      },
      {
	"name": "FACE_2",
	"file": "images/sillywalks/02.png",
	"type": "png"
      },
      {
	"name": "FACE_3",
	"file": "images/sillywalks/03.png",
	"type": "png"
      },
      {
	"name": "FACE_4",
	"file": "images/sillywalks/04.png",
	"type": "png"
      },
      {
	"name": "FACE_5",
	"file": "images/sillywalks/05.png",
	"type": "png"
      },
      {
	"name": "FACE_6",
	"file": "images/sillywalks/06.png",
	"type": "png"
      },
      {
	"name": "FACE_7",
	"file": "images/sillywalks/07.png",
	"type": "png"
      },
      {
	"name": "FACE_8",
	"file": "images/sillywalks/08.png",
	"type": "png"
      },
      {
	"name": "FACE_9",
	"file": "images/sillywalks/09.png",
	"type": "png"
      },
      {
	"name": "FACE_10",
	"file": "images/sillywalks/10.png",
	"type": "png"
      },
      {
	"name": "FACE_11",
	"file": "images/sillywalks/11.png",
	"type": "png"
      }
    ]
  }
}
